monads/__init__.py
monads/applicative.py
monads/currying.py
monads/functor.py
monads/future.py
monads/list.py
monads/maybe.py
monads/monad.py
monads/monoid.py
monads/py.typed
monads/reader.py
monads/result.py
typesafe_monads-0.8.dist-info/LICENSE
typesafe_monads-0.8.dist-info/METADATA
typesafe_monads-0.8.dist-info/WHEEL
typesafe_monads-0.8.dist-info/top_level.txt
typesafe_monads-0.8.dist-info/RECORD
