Metadata-Version: 2.1
Name: typesafe-monads
Version: 0.8
Summary: Type-annotated monad implementations for Python 3.7+
Home-page: https://github.com/correl/typesafe-monads
Author: Correl Roush
Author-email: correl@gmail.com
License: UNKNOWN
Platform: UNKNOWN
Classifier: Development Status :: 2 - Pre-Alpha
Classifier: Intended Audience :: Developers
Classifier: License :: OSI Approved :: MIT License
Classifier: Operating System :: OS Independent
Classifier: Programming Language :: Python :: 3 :: Only
Classifier: Programming Language :: Python :: 3.7
Classifier: Programming Language :: Python :: 3.8
Classifier: Topic :: Software Development :: Libraries
